Workbook

Sheet Dishes
A1: Dish_ID | B1: Dish_Name | C1: Category | D1: Price | E1: Production_Cost | F1: Available(Y/N)
A2: D_001 | B2: Butter chicken | C2: Non-Veg | D2: 240 | E2: =SUMIF(Recipe_map!$B:$B,A2,Recipe_map!$G:$G) -> 103.4878
A3: D_002 | B3: Kadhai Chicken | C3: Non-Veg | D3: 230 | E3: =SUMIF(Recipe_map!$B:$B,A3,Recipe_map!$G:$G) -> 70.8269
A4: D_003 | B4: Chicken Korma | C4: Non-Veg | D4: 180 | E4: =SUMIF(Recipe_map!$B:$B,A4,Recipe_map!$G:$G) -> 88.9566
A5: D_004 | B5: Chicken Biryani | C5: Non-Veg | D5: 200 | E5: =SUMIF(Recipe_map!$B:$B,A5,Recipe_map!$G:$G) -> 168.3737
A6: D_005 | B6: Chilli Chicken | C6: Non-Veg | D6: 180 | E6: =SUMIF(Recipe_map!$B:$B,A6,Recipe_map!$G:$G) -> 53.468
A7: D_006 | B7: Chicken Kabab | C7: Non-Veg | D7: 180 | E7: =SUMIF(Recipe_map!$B:$B,A7,Recipe_map!$G:$G) -> 61.4987
A8: D_007 | B8: Roasted Chicken | C8: Non-Veg | D8: 350 | E8: =SUMIF(Recipe_map!$B:$B,A8,Recipe_map!$G:$G) -> 64.1397
A9: D_008 | B9: Dal Tadka | C9: Veg | D9: 160 | E9: =SUMIF(Recipe_map!$B:$B,A9,Recipe_map!$G:$G) -> 19.5013
A10: D_009 | B10: Dal makhani | C10: Veg | E10: =SUMIF(Recipe_map!$B:$B,A10,Recipe_map!$G:$G) -> 44.1655
A11: D_010 | B11: Kadhai Paneer | C11: Veg | E11: =SUMIF(Recipe_map!$B:$B,A11,Recipe_map!$G:$G) -> 78.1257
A12: D_011 | B12: Paneer Butter Masala | C12: Veg | E12: =SUMIF(Recipe_map!$B:$B,A12,Recipe_map!$G:$G) -> 104.139
A13: D_012 | B13: Veg Biryani | C13: Veg | E13: =SUMIF(Recipe_map!$B:$B,A13,Recipe_map!$G:$G) -> 24.8984
A14: D_013 | B14: Mix Veg | C14: Veg | E14: =SUMIF(Recipe_map!$B:$B,A14,Recipe_map!$G:$G) -> 19.994
A15: D_014 | B15: Rajma | C15: Veg | E15: =SUMIF(Recipe_map!$B:$B,A15,Recipe_map!$G:$G) -> 27.7768
A16: D_015 | B16: Curry Pakoda | C16: Veg | E16: =SUMIF(Recipe_map!$B:$B,A16,Recipe_map!$G:$G) -> 20.5143
A17: D_016 | B17: Aloo Bharta | C17: Veg | E17: =SUMIF(Recipe_map!$B:$B,A17,Recipe_map!$G:$G) -> 11.4215
A18: D_017 | B18: Baigan Bharta | C18: Veg | E18: =SUMIF(Recipe_map!$B:$B,A18,Recipe_map!$G:$G) -> 21.7505
A19: D_018 | B19: Roti | C19: Breads | E19: =SUMIF(Recipe_map!$B:$B,A19,Recipe_map!$G:$G) -> 3.7256
A20: D_019 | B20: Paratha | C20: Breads | E20: =SUMIF(Recipe_map!$B:$B,A20,Recipe_map!$G:$G) -> 6.007
A21: D_020 | B21: Lacha Paratha | C21: Breads | E21: =SUMIF(Recipe_map!$B:$B,A21,Recipe_map!$G:$G) -> 6.574
... A26: D_025 | B26: Kheer | C26: Dessert | E26: =SUMIF(Recipe_map!$B:$B,A26,Recipe_map!$G:$G) -> 85.721

Sheet Ingredients
A1: Ingredient_ID | B1: Ingredient_name | C1: Current_stock(kg) | D1: Safety_Stock_level(kg) | E1: Reorder_delay(days) | F1: Supplier_id | G1: Cost/kg | H1: Shelf_life(days)
A2: I_001 | B2: Rice | C2: 151 | D2: 40 | E2: 3 | F2: SUP01 | G2: 60 | H2: 365
A3: I_002 | B3: Black pepper | C3: 1.9 | D3: 0.764 | E3: 5 | F3: SUP03 | G3: 900 | H3: 730
A4: I_003 | B4: Butter | C4: 42 | D4: 13 | E4: 2 | F4: SUP02 | G4: 480 | H4: 60
A5: I_004 | B5: Capsicum | C5: 18 | D5: 7.3 | E5: 1 | F5: SUP04 | G5: 60 | H5: 10
A6: I_005 | B6: Cardamom | C6: 1.3 | D6: 0.531 | E6: 5 | F6: SUP03 | G6: 2200 | H6: 730
A7: I_006 | B7: Cashew | C7: 22 | D7: 7.2 | E7: 4 | F7: SUP03 | G7: 950 | H7: 180
A8: I_007 | B8: Chicken | C8: 72 | D8: 36 | E8: 1 | F8: SUP05 | G8: 220 | H8: 3
A9: I_008 | B9: Coriander | C9: 2.6 | D9: 1.3 | E9: 1 | F9: SUP04 | G9: 40 | H9: 5
A10: I_009 | B10: Coriander powder | C10: 14 | D10: 5.6 | E10: 5 | F10: SUP03 | G10: 280 | H10: 365
A11: I_010 | B11: Cream | C11: 20 | D11: 12 | E11: 2 | F11: SUP02 | G11: 320 | H11: 15
A12: I_011 | B12: Cumin | C12: 16 | D12: 6.3 | E12: 5 | F12: SUP03 | G12: 400 | H12: 365
A13: I_012 | B13: Garam masala | C13: 26 | D13: 10 | E13: 5 | F13: SUP03 | G13: 600 | H13: 365
... A35: I_034 | B35: Brinjal | C35: 6.5 | D35: 3.2 | E35: 1 | F35: SUP04 | G35: 40 | H35: 7

Sheet Recipe_map
A1: Row_ID | B1: Dish_ID | C1: Ingredient_ID | D1: Quantity_per_unit(kg) | E1: Randomness_margin(%) | F1: Final_Quantity(kg) | G1: Ingredient_Cost(₹)
A2: R_001 | B2: D_001 | C2: I_007 | D2: 0.18 | E2: 6 | F2: =D2*(1+E2/100) -> 0.1908 | G2: =F2*INDEX(Ingredients!$G:$G,MATCH(C2,Ingredients!$A:$A,0)) -> 41.976
A3: R_002 | B3: D_001 | C3: I_003 | D3: 0.025 | E3: 5 | F3: =D3*(1+E3/100) -> 0.02625 | G3: =F3*INDEX(Ingredients!$G:$G,MATCH(C3,Ingredients!$A:$A,0)) -> 12.6
A4: R_003 | B4: D_001 | C4: I_019 | D4: 0.015 | E4: 5 | F4: =D4*(1+E4/100) -> 0.01575 | G4: =F4*INDEX(Ingredients!$G:$G,MATCH(C4,Ingredients!$A:$A,0)) -> 2.835
A5: R_004 | B5: D_001 | C5: I_020 | D5: 0.05 | E5: 8 | F5: =D5*(1+E5/100) -> 0.054 | G5: =F5*INDEX(Ingredients!$G:$G,MATCH(C5,Ingredients!$A:$A,0)) -> 1.89
A6: R_005 | B6: D_001 | C6: I_026 | D6: 0.06 | E6: 8 | F6: =D6*(1+E6/100) -> 0.0648 | G6: =F6*INDEX(Ingredients!$G:$G,MATCH(C6,Ingredients!$A:$A,0)) -> 1.944
A7: R_006 | B7: D_001 | C7: I_014 | D7: 0.012 | E7: 8 | F7: =D7*(1+E7/100) -> 0.01296 | G7: =F7*INDEX(Ingredients!$G:$G,MATCH(C7,Ingredients!$A:$A,0)) -> 1.5552
A8: R_007 | B8: D_001 | C8: I_013 | D8: 0.012 | E8: 8 | F8: =D8*(1+E8/100) -> 0.01296 | G8: =F8*INDEX(Ingredients!$G:$G,MATCH(C8,Ingredients!$A:$A,0)) -> 1.944
A9: R_008 | B9: D_001 | C9: I_006 | D9: 0.015 | E9: 4 | F9: =D9*(1+E9/100) -> 0.0156 | G9: =F9*INDEX(Ingredients!$G:$G,MATCH(C9,Ingredients!$A:$A,0)) -> 14.82
A10: R_009 | B10: D_001 | C10: I_010 | D10: 0.035 | E10: 6 | F10: =D10*(1+E10/100) -> 0.0371 | G10: =F10*INDEX(Ingredients!$G:$G,MATCH(C10,Ingredients!$A:$A,0)) -> 11.872
A11: R_010 | B11: D_001 | C11: I_029 | D11: 0.04 | E11: 6 | F11: =D11*(1+E11/100) -> 0.0424 | G11: =F11*INDEX(Ingredients!$G:$G,MATCH(C11,Ingredients!$A:$A,0)) -> 2.968
A12: R_011 | B12: D_001 | C12: I_012 | D12: 0.006 | E12: 3 | F12: =D12*(1+E12/100) -> 0.00618 | G12: =F12*INDEX(Ingredients!$G:$G,MATCH(C12,Ingredients!$A:$A,0)) -> 3.708
A13: R_012 | B13: D_001 | C13: I_009 | D13: 0.006 | E13: 3 | F13: =D13*(1+E13/100) -> 0.00618 | G13: =F13*INDEX(Ingredients!$G:$G,MATCH(C13,Ingredients!$A:$A,0)) -> 1.7304
... A256: R_255 | B256: D_025 | C256: I_006 | D256: 0.008 | E256: 4 | F256: =D256*(1+E256/100) -> 0.00832 | G256: =F256*INDEX(Ingredients!$G:$G,MATCH(C256,Ingredients!$A:$A,0)) -> 7.904

Sheet Sales_Data
A1: Date | B1: Dish_ID | C1: Units_Sold
A2: 2026-06-23 | B2: D_001 | C2: 36
A3: 2026-06-23 | B3: D_002 | C3: 15
A4: 2026-06-23 | B4: D_003 | C4: 18
A5: 2026-06-23 | B5: D_004 | C5: 35
A6: 2026-06-23 | B6: D_005 | C6: 19
A7: 2026-06-23 | B7: D_006 | C7: 16
A8: 2026-06-23 | B8: D_007 | C8: 12
A9: 2026-06-23 | B9: D_008 | C9: 20
A10: 2026-06-23 | B10: D_009 | C10: 24
A11: 2026-06-23 | B11: D_010 | C11: 20
A12: 2026-06-23 | B12: D_011 | C12: 31
A13: 2026-06-23 | B13: D_012 | C13: 14
... A1501: 2026-08-21 | B1501: D_025 | C1501: 13
